dwave_embedding_utilities.py
dwave_embedding_utilities-0.3.0.dist-info/DESCRIPTION.rst
dwave_embedding_utilities-0.3.0.dist-info/METADATA
dwave_embedding_utilities-0.3.0.dist-info/RECORD
dwave_embedding_utilities-0.3.0.dist-info/WHEEL
dwave_embedding_utilities-0.3.0.dist-info/metadata.json
dwave_embedding_utilities-0.3.0.dist-info/top_level.txt
