Metadata-Version: 2.0
Name: dwave-embedding-utilities
Version: 0.3.0
Summary: Utilities to manage embedding for the D-Wave System
Home-page: https://github.com/dwavesystems/dwave_embedding_utilities
Author: D-Wave Systems Inc.
Author-email: acondello@dwavesys.com
License: Apache 2.0
Platform: UNKNOWN
